mail_sanitizer/__init__.py
mail_sanitizer/mail_dump_ops.py
mail_sanitizer/main.py
mail_sanitizer/utils.py
mail_sanitizer/clients/__init__.py
mail_sanitizer/clients/gmail_client.py
mail_sanitizer-0.0.7.dist-info/LICENSE
mail_sanitizer-0.0.7.dist-info/METADATA
mail_sanitizer-0.0.7.dist-info/WHEEL
mail_sanitizer-0.0.7.dist-info/entry_points.txt
mail_sanitizer-0.0.7.dist-info/top_level.txt
mail_sanitizer-0.0.7.dist-info/RECORD
